base64file/__init__.py
base64file/base64_file.py
base64file/base85_file.py
base64file/chacha20_file.py
base64file/convenience.py
base64file-0.0.12.dist-info/LICENSE
base64file-0.0.12.dist-info/WHEEL
base64file-0.0.12.dist-info/METADATA
base64file-0.0.12.dist-info/RECORD
