Metadata-Version: 2.1
Name: base64file
Version: 0.0.12
Summary: An IO wrapper that reads/writes binary data as base64 into a text file
Author-email: Avery Khoo <averykhoo@gmail.com>
Classifier: License :: OSI Approved :: MIT License
Project-URL: Home, https://github.com/averykhoo/base64file
